setupextras/__init__.py
setupextras/extras.py
setupextras/tests/__init__.py
setupextras/tests/__main__.py
setupextras/tests/helper.py
setupextras/tests/test_setupextras.py
setupextras/tests/__fixtures__/py-foo/MIT-LICENSE
setupextras/tests/__fixtures__/py-foo/README.md
setupextras/tests/__fixtures__/py-foo/requirements.txt
setupextras/tests/__fixtures__/py-foo/setup.py
setupextras/tests/__fixtures__/py-foo/bin/foo
setupextras/tests/__fixtures__/py-foo/foo/__init__.py
setupextras/tests/__fixtures__/py-foo/foo/foo.py
setupextras/tests/__fixtures__/py-foo/foo/tests/__init__.py
setupextras/tests/__fixtures__/py-foo/foo/tests/__main__.py
setupextras/tests/__fixtures__/py-foo/foo/tests/test_foo.py
setupextras/tests/__fixtures__/py-foo/foo/tests/__fixtures__/foo.txt
setupextras/tests/__fixtures__/py-foo/foo/tests/__fixtures__/foo/bar.txt
setupextras/tests/__fixtures__/py-foo/foo/tests/__fixtures__/foo/baz.txt
setupextras-0.1.5.data/data/setupextras/tests/__fixtures__/setupextras/tests/__fixtures__/py-foo/README.md
setupextras-0.1.5.data/data/setupextras/tests/__fixtures__/setupextras/tests/__fixtures__/py-foo/requirements.txt
setupextras-0.1.5.data/data/setupextras/tests/__fixtures__/setupextras/tests/__fixtures__/py-foo/setup.py
setupextras-0.1.5.data/data/setupextras/tests/__fixtures__/setupextras/tests/__fixtures__/py-foo/foo/__init__.py
setupextras-0.1.5.data/data/setupextras/tests/__fixtures__/setupextras/tests/__fixtures__/py-foo/foo/foo.py
setupextras-0.1.5.data/data/setupextras/tests/__fixtures__/setupextras/tests/__fixtures__/py-foo/foo/tests/__init__.py
setupextras-0.1.5.data/data/setupextras/tests/__fixtures__/setupextras/tests/__fixtures__/py-foo/foo/tests/__main__.py
setupextras-0.1.5.data/data/setupextras/tests/__fixtures__/setupextras/tests/__fixtures__/py-foo/foo/tests/test_foo.py
setupextras-0.1.5.data/data/setupextras/tests/__fixtures__/setupextras/tests/__fixtures__/py-foo/foo/tests/__fixtures__/foo.txt
setupextras-0.1.5.dist-info/METADATA
setupextras-0.1.5.dist-info/WHEEL
setupextras-0.1.5.dist-info/top_level.txt
setupextras-0.1.5.dist-info/zip-safe
setupextras-0.1.5.dist-info/RECORD
